ksup_analyzer-0.3.4.dist-info/METADATA
ksup_analyzer-0.3.4.dist-info/WHEEL
ksup_analyzer-0.3.4.dist-info/licenses/LICENSE
ksup_analyzer/__init__.py
ksup_analyzer/event/Driver.py
ksup_analyzer/event/Event.py
ksup_analyzer/event/LineUp.py
ksup_analyzer/event/Result.py
ksup_analyzer/event/__init__.py
ksup_analyzer/plots/Plots.py
ksup_analyzer/plots/__init__.py
ksup_analyzer/replay/FileHandler.py
ksup_analyzer/replay/ReplayFile.py
ksup_analyzer/replay/__init__.py
ksup_analyzer-0.3.4.dist-info/RECORD
